<!-- Technosciences Database -->
<!-- 
   domain:
         rdAerospaceengineering
         rdAstroEngineering
         rdBiosciences
         rdCulture
         rdEcosciences
         rdIndustrialTechnologies
         rdNanotechnology
         rdPhysics

      rfield:
         rf1AerospaceTechnics
         rf1SpaceArchitecture
         rf1SpaceDrives
         
         rf2Astrophysics
         rf2SpaceEngineering
         
         rf3Biotechnologies
         rf3Medicine
         rf3Neuroscience
   
         rf4Communication
         rf4Entertainment
         rf4MemeticEngineering
         
         rf5Ecology
         rf5Planetology
         
         rf6Automation
         rf6Computing
         rf6IndustrialTechnics
         rf6Materials
         
         rf7MechanicalNanotechnology
         rf7MolecularNanotechnology
         rf7Nanomaterials
         
         rf8Energy
         rf8NuclearPhysics
         rf8ParticlesPhysics

      influence projection type
         iptProduct
         iptInfrastructure
         iptSpaceUnitArchitecture
         iptEquipmentModule
         iptSPMItem
         
   <tsci theory="" token="" domain="" field="" techlevel="" difficulty="" discothres="" maxRTSpoints="">
      <rts token="" domain="" rfield="" isKeyTech="" influence=""/>
      <influenceproj token="" type=""/>
   </tsci>
-->
<technosciences>
   <!-- Astronomy -->
   <tsci theory="False" token="tsAstronomy" domain="domainAstroEngineering" field="rfieldAstrophysics" techlevel="1" difficulty="0" discothres="0" maxRTSpoints="0">
   </tsci>
   <!-- Basic Ecology -->
   <tsci theory="False" token="tsBasicEco" domain="domainEcosciences" field="rfieldEcology" techlevel="1" difficulty="0" discothres="0" maxRTSpoints="0">
      <influenceproj token="equipHumidityTrap1" type="iptProduct"/>
      <influenceproj token="equipHumidityTrap2" type="iptProduct"/>
      <influenceproj token="equipHumidityTrap3" type="iptProduct"/>
      <influenceproj token="equipHumidityTrap4" type="iptProduct"/>
      <influenceproj token="equipHumidityTrap5" type="iptProduct"/>
   </tsci>
   <!-- Automation -->
   <tsci theory="False" token="tsAutomation" domain="rdIndustrialTechnologies" field="rf6Automation" techlevel="1" difficulty="0" discothres="0" maxRTSpoints="0">
   </tsci>
   <!-- Basic Mining & Refining -->
   <tsci theory="False" token="tsBasicMinRef" domain="domainIndustrialTechnologies" field="rfieldIndustrialTechnics" techlevel="1" difficulty="0" discothres="0" maxRTSpoints="0">
      <influenceproj token="infrMiningSite" type="iptInfrastructure"/>
      <influenceproj token="equipMiningMachinery" type="iptProduct"/>
   </tsci>
   <!-- Alloys -->
   <tsci theory="False" token="tsAlloys" domain="domainIndustrialTechnologies" field="rfieldMaterials" techlevel="1" difficulty="0" discothres="0" maxRTSpoints="0">
      <influenceproj token="matAluminium" type="iptProduct"/>
      <influenceproj token="matGold" type="iptProduct"/>
      <influenceproj token="matSilver" type="iptProduct"/>
      <influenceproj token="matSteel" type="iptProduct"/>
      <influenceproj token="matTitanium" type="iptProduct"/>
      <influenceproj token="equipMultiDepot1" type="iptProduct"/>
      <influenceproj token="equipMultiDepot2" type="iptProduct"/>
      <influenceproj token="equipMultiDepot3" type="iptProduct"/>
      <influenceproj token="equipMultiDepot4" type="iptProduct"/>
      <influenceproj token="equipMultiDepot5" type="iptProduct"/>
   </tsci>
</technosciences>
